pulse_pal/__init__.py
pulse_pal/cli.py
pulse_pal/pulse_pal.py
pulse_pal/scripts.py
pulse_pal-0.0.6.dist-info/LICENSE
pulse_pal-0.0.6.dist-info/METADATA
pulse_pal-0.0.6.dist-info/WHEEL
pulse_pal-0.0.6.dist-info/entry_points.txt
pulse_pal-0.0.6.dist-info/top_level.txt
pulse_pal-0.0.6.dist-info/RECORD
