Metadata-Version: 2.1
Name: pulse-pal
Version: 0.0.6
Summary: Unofficial port of Pulse Pal for Python 3
Home-page: https://github.com/mmyros/pulse_pal
Author: Maxym Myroshnychenko
Author-email: mmyros@gmail.com
License: MIT license
Keywords: pulse_pal
Platform: UNKNOWN
Classifier: Development Status :: 2 - Pre-Alpha
Classifier: Intended Audience :: Developers
Classifier: License :: OSI Approved :: MIT License
Classifier: Natural Language :: English
Classifier: Programming Language :: Python :: 3
Classifier: Programming Language :: Python :: 3.5
Classifier: Programming Language :: Python :: 3.6
Classifier: Programming Language :: Python :: 3.7
Classifier: Programming Language :: Python :: 3.8
Requires-Python: >=3.5
Requires-Dist: Click (>=7.0)
Requires-Dist: pyserial
